{
    "OpenJTalkResources":[
        {
            "Name": "女声: tohoku-f01",
            "Id": "tohoku-f01",
            "Terms": "https://github.com/icn-lab/htsvoice-tohoku-f01/blob/master/COPYRIGHT.txt",
            "FileSize": "",
            "Author": "東北大学 伊藤・能勢研究室(ICN Lab.)",
            "ContentId": "",
            "StylePaths": {
                "neutral" : "tohoku-f01-neutral.htsvoice",
                "happy" : "tohoku-f01-happy.htsvoice",
                "angry" : "tohoku-f01-angry.htsvoice",
                "sad" : "tohoku-f01-sad.htsvoice"
            }
        },
        {
            "Name": "男声: M001",
            "Id": "nitech_jp_atr503_m001",
            "Terms": "https://open-jtalk.sourceforge.net/",
            "FileSize": "",
            "Author": "HTS Working Group",
            "ContentId": "",
            "StylePaths": {
                "normal": "nitech_jp_atr503_m001.htsvoice"
            }
        },
        {
            "Name": "女性: メイ",
            "Id": "mei",
            "Terms": "https://www.mmdagent.jp/",
            "FileSize": "",
            "Author": "MMDAgent Project Team",
            "ContentId": "sm14317331",
            "StylePaths": {
                "normal": "mei_normal.htsvoice",
                "angry": "mei_angry.htsvoice",
                "happy": "mei_happy.htsvoice",
                "sad": "mei_sad.htsvoice",
                "bashful": "mei_bashful.htsvoice"
            }
        },
        {
            "Name": "男声: タクミ",
            "Id": "takumi",
            "Terms": "https://www.mmdagent.jp/",
            "FileSize": "",
            "Author": "MMDAgent Project Team",
            "ContentId": "sm14317331",
            "StylePaths": {
                "normal": "takumi_normal.htsvoice",
                "angry": "takumi_angry.htsvoice",
                "happy": "takumi_happy.htsvoice",
                "sad": "takumi_sad.htsvoice"
            }
        }
    ]
}